django_parser/models.py
django_parser/utils.py
django_parser/views.py
django_parser/__init__.py
django_parser/templatetags/hightlight.py
django_parser/templatetags/__init__.py
django_parser-0.3.dist-info/metadata.json
django_parser-0.3.dist-info/zip-safe
django_parser-0.3.dist-info/DESCRIPTION.rst
django_parser-0.3.dist-info/top_level.txt
django_parser-0.3.dist-info/WHEEL
django_parser-0.3.dist-info/RECORD
django_parser-0.3.dist-info/METADATA
