Metadata-Version: 2.0
Name: django-parser
Version: 0.3
Summary: html sanitiezer from djang0byte
Home-page: https://github.com/nvbn/djang0parser
Author: Vladimir Yakovlev
Author-email: nvbn.rm@gmail.com
License: GPL
Keywords: django
Platform: UNKNOWN
Requires-Dist: BeautifulSoup
Requires-Dist: Pygments
